mud/__init__.py
mud/__main__.py
mud/advancement.py
mud/config.py
mud/entrypoint.py
mud/game_loop.py
mud/game_tick_scheduler.py
mud/handler.py
mud/logging.py
mud/mob_cmds.py
mud/mobprog.py
mud/notes.py
mud/persistence.py
mud/registry.py
mud/rom_api.py
mud/server.py
mud/spec_funs.py
mud/time.py
mud/wiznet.py
mud/account/__init__.py
mud/account/account_manager.py
mud/account/account_service.py
mud/admin_logging/__init__.py
mud/admin_logging/admin.py
mud/admin_logging/agent_trace.py
mud/affects/engine.py
mud/affects/saves.py
mud/agent/__init__.py
mud/agent/agent_protocol.py
mud/agent/character_agent.py
mud/ai/__init__.py
mud/ai/aggressive.py
mud/characters/__init__.py
mud/characters/conditions.py
mud/characters/follow.py
mud/combat/__init__.py
mud/combat/assist.py
mud/combat/death.py
mud/combat/engine.py
mud/combat/kill_table.py
mud/combat/messages.py
mud/combat/safety.py
mud/commands/__init__.py
mud/commands/admin_commands.py
mud/commands/advancement.py
mud/commands/affects.py
mud/commands/alias_cmds.py
mud/commands/auto_settings.py
mud/commands/build.py
mud/commands/channels.py
mud/commands/character.py
mud/commands/combat.py
mud/commands/communication.py
mud/commands/compare.py
mud/commands/consider.py
mud/commands/consumption.py
mud/commands/decorators.py
mud/commands/dispatcher.py
mud/commands/doors.py
mud/commands/equipment.py
mud/commands/feedback.py
mud/commands/give.py
mud/commands/group_commands.py
mud/commands/healer.py
mud/commands/help.py
mud/commands/imc.py
mud/commands/imm_admin.py
mud/commands/imm_commands.py
mud/commands/imm_display.py
mud/commands/imm_emote.py
mud/commands/imm_load.py
mud/commands/imm_olc.py
mud/commands/imm_punish.py
mud/commands/imm_search.py
mud/commands/imm_server.py
mud/commands/imm_set.py
mud/commands/info.py
mud/commands/info_extended.py
mud/commands/inspection.py
mud/commands/inventory.py
mud/commands/liquids.py
mud/commands/magic_items.py
mud/commands/misc_info.py
mud/commands/misc_player.py
mud/commands/mobprog_tools.py
rom24_quickmud_python-2.5.4.dist-info/licenses/LICENSE
rom24_quickmud_python-2.5.4.dist-info/METADATA
rom24_quickmud_python-2.5.4.dist-info/WHEEL
rom24_quickmud_python-2.5.4.dist-info/entry_points.txt
rom24_quickmud_python-2.5.4.dist-info/top_level.txt
rom24_quickmud_python-2.5.4.dist-info/RECORD
