Metadata-Version: 2.4
Name: rom24-quickmud-python
Version: 2.5.4
Summary: A modern Python port of the ROM 2.4b6 MUD engine with full telnet server and JSON world loading
Author-email: Mark Jedrzejczyk <mark.jedrzejczyk@gmail.com>
Maintainer-email: Mark Jedrzejczyk <mark.jedrzejczyk@gmail.com>
License-Expression: MIT
Project-URL: Homepage, https://github.com/Nostoi/rom24-quickmud-python
Project-URL: Repository, https://github.com/Nostoi/rom24-quickmud-python.git
Project-URL: Documentation, https://github.com/Nostoi/rom24-quickmud-python/blob/master/README.md
Project-URL: Bug Tracker, https://github.com/Nostoi/rom24-quickmud-python/issues
Project-URL: Changelog, https://github.com/Nostoi/rom24-quickmud-python/releases
Keywords: mud,rom,game,mmo,telnet,server
Classifier: Development Status :: 4 - Beta
Classifier: Environment :: Console
Classifier: Environment :: No Input/Output (Daemon)
Classifier: Intended Audience :: Developers
Classifier: Intended Audience :: End Users/Desktop
Classifier: Operating System :: OS Independent
Classifier: Programming Language :: Python :: 3
Classifier: Programming Language :: Python :: 3.10
Classifier: Programming Language :: Python :: 3.11
Classifier: Programming Language :: Python :: 3.12
Classifier: Topic :: Games/Entertainment :: Multi-User Dungeons (MUD)
Classifier: Topic :: Internet
Classifier: Topic :: Software Development :: Libraries :: Python Modules
Classifier: Typing :: Typed
Requires-Python: >=3.10
License-File: LICENSE
Requires-Dist: SQLAlchemy<3,>=2.0
Requires-Dist: typer>=0.9
Requires-Dist: python-dotenv>=1.0
Requires-Dist: fastapi>=0.68.0
Requires-Dist: uvicorn>=0.15.0
Requires-Dist: pytest-timeout>=2.1.0
Requires-Dist: asyncssh>=2.0
Provides-Extra: dev
Requires-Dist: pytest>=8.0; extra == "dev"
Requires-Dist: pytest-cov>=6.0; extra == "dev"
Requires-Dist: pytest-timeout>=2.1.0; extra == "dev"
Requires-Dist: mypy>=1.0; extra == "dev"
Requires-Dist: ruff>=0.1.0; extra == "dev"
Requires-Dist: black>=22.0; extra == "dev"
Requires-Dist: jsonschema>=4.0; extra == "dev"
Requires-Dist: build>=0.10.0; extra == "dev"
Requires-Dist: twine>=4.0.0; extra == "dev"
Provides-Extra: test
Requires-Dist: pytest>=8.0; extra == "test"
Requires-Dist: pytest-cov>=6.0; extra == "test"
Requires-Dist: pytest-timeout>=2.1.0; extra == "test"
Dynamic: license-file
